<?xml version="1.0" encoding="utf-8"?>
<TextureAtlas imagePath="invisible.png">
	<!-- Created with Adobe Animate version 19.2.1.408 -->
	<!-- http://www.adobe.com/products/animate.html -->
	<SubTexture name="BF NOTE DOWN00000" x="0" y="0" width="0" height="0" frameX="-107374182" frameY="-107374182" frameWidth="0" frameHeight="0"/>
	<SubTexture name="BF NOTE DOWN00001" x="0" y="0" width="0" height="0" frameX="-107374182" frameY="-107374182" frameWidth="0" frameHeight="0"/>
	<SubTexture name="BF NOTE DOWN00002" x="0" y="0" width="0" height="0" frameX="-107374182" frameY="-107374182" frameWidth="0" frameHeight="0"/>
	<SubTexture name="BF NOTE DOWN00003" x="0" y="0" width="0" height="0" frameX="-107374182" frameY="-107374182" frameWidth="0" frameHeight="0"/>
	<SubTexture name="BF NOTE DOWN00004" x="0" y="0" width="0" height="0" frameX="-107374182" frameY="-107374182" frameWidth="0" frameHeight="0"/>
	<SubTexture name="BF NOTE DOWN00005" x="0" y="0" width="0" height="0" frameX="-107374182" frameY="-107374182" frameWidth="0" frameHeight="0"/>
	<SubTexture name="BF NOTE DOWN00006" x="0" y="0" width="0" height="0" frameX="-107374182" frameY="-107374182" frameWidth="0" frameHeight="0"/>
	<SubTexture name="BF NOTE DOWN00007" x="0" y="0" width="0" height="0" frameX="-107374182" frameY="-107374182" frameWidth="0" frameHeight="0"/>
	<SubTexture name="BF NOTE DOWN00008" x="0" y="0" width="0" height="0" frameX="-107374182" frameY="-107374182" frameWidth="0" frameHeight="0"/>
	<SubTexture name="BF NOTE DOWN00009" x="0" y="0" width="0" height="0" frameX="-107374182" frameY="-107374182" frameWidth="0" frameHeight="0"/>
	<SubTexture name="BF NOTE DOWN00010" x="0" y="0" width="0" height="0" frameX="-107374182" frameY="-107374182" frameWidth="0" frameHeight="0"/>
	<SubTexture name="BF NOTE DOWN00011" x="0" y="0" width="0" height="0" frameX="-107374182" frameY="-107374182" frameWidth="0" frameHeight="0"/>
	<SubTexture name="BF NOTE DOWN00012" x="0" y="0" width="0" height="0" frameX="-107374182" frameY="-107374182" frameWidth="0" frameHeight="0"/>
	<SubTexture name="BF NOTE DOWN00013" x="0" y="0" width="0" height="0" frameX="-107374182" frameY="-107374182" frameWidth="0" frameHeight="0"/>
	<SubTexture name="BF NOTE DOWN00014" x="0" y="0" width="0" height="0" frameX="-107374182" frameY="-107374182" frameWidth="0" frameHeight="0"/>
	<SubTexture name="BF NOTE DOWN00015" x="0" y="0" width="0" height="0" frameX="-107374182" frameY="-107374182" frameWidth="0" frameHeight="0"/>
	<SubTexture name="BF NOTE LEFT00000" x="0" y="0" width="0" height="0" frameX="-107374182" frameY="-107374182" frameWidth="0" frameHeight="0"/>
	<SubTexture name="BF NOTE LEFT00001" x="0" y="0" width="0" height="0" frameX="-107374182" frameY="-107374182" frameWidth="0" frameHeight="0"/>
	<SubTexture name="BF NOTE LEFT00002" x="0" y="0" width="0" height="0" frameX="-107374182" frameY="-107374182" frameWidth="0" frameHeight="0"/>
	<SubTexture name="BF NOTE LEFT00003" x="0" y="0" width="0" height="0" frameX="-107374182" frameY="-107374182" frameWidth="0" frameHeight="0"/>
	<SubTexture name="BF NOTE LEFT00004" x="0" y="0" width="0" height="0" frameX="-107374182" frameY="-107374182" frameWidth="0" frameHeight="0"/>
	<SubTexture name="BF NOTE LEFT00005" x="0" y="0" width="0" height="0" frameX="-107374182" frameY="-107374182" frameWidth="0" frameHeight="0"/>
	<SubTexture name="BF NOTE LEFT00006" x="0" y="0" width="0" height="0" frameX="-107374182" frameY="-107374182" frameWidth="0" frameHeight="0"/>
	<SubTexture name="BF NOTE LEFT00007" x="0" y="0" width="0" height="0" frameX="-107374182" frameY="-107374182" frameWidth="0" frameHeight="0"/>
	<SubTexture name="BF NOTE LEFT00008" x="0" y="0" width="0" height="0" frameX="-107374182" frameY="-107374182" frameWidth="0" frameHeight="0"/>
	<SubTexture name="BF NOTE LEFT00009" x="0" y="0" width="0" height="0" frameX="-107374182" frameY="-107374182" frameWidth="0" frameHeight="0"/>
	<SubTexture name="BF NOTE LEFT00010" x="0" y="0" width="0" height="0" frameX="-107374182" frameY="-107374182" frameWidth="0" frameHeight="0"/>
	<SubTexture name="BF NOTE LEFT00011" x="0" y="0" width="0" height="0" frameX="-107374182" frameY="-107374182" frameWidth="0" frameHeight="0"/>
	<SubTexture name="BF NOTE LEFT00012" x="0" y="0" width="0" height="0" frameX="-107374182" frameY="-107374182" frameWidth="0" frameHeight="0"/>
	<SubTexture name="BF NOTE LEFT00013" x="0" y="0" width="0" height="0" frameX="-107374182" frameY="-107374182" frameWidth="0" frameHeight="0"/>
	<SubTexture name="BF NOTE LEFT00014" x="0" y="0" width="0" height="0" frameX="-107374182" frameY="-107374182" frameWidth="0" frameHeight="0"/>
	<SubTexture name="BF NOTE LEFT00015" x="0" y="0" width="0" height="0" frameX="-107374182" frameY="-107374182" frameWidth="0" frameHeight="0"/>
	<SubTexture name="BF NOTE RIGHT00000" x="0" y="0" width="0" height="0" frameX="-107374182" frameY="-107374182" frameWidth="0" frameHeight="0"/>
	<SubTexture name="BF NOTE RIGHT00001" x="0" y="0" width="0" height="0" frameX="-107374182" frameY="-107374182" frameWidth="0" frameHeight="0"/>
	<SubTexture name="BF NOTE RIGHT00002" x="0" y="0" width="0" height="0" frameX="-107374182" frameY="-107374182" frameWidth="0" frameHeight="0"/>
	<SubTexture name="BF NOTE RIGHT00003" x="0" y="0" width="0" height="0" frameX="-107374182" frameY="-107374182" frameWidth="0" frameHeight="0"/>
	<SubTexture name="BF NOTE RIGHT00004" x="0" y="0" width="0" height="0" frameX="-107374182" frameY="-107374182" frameWidth="0" frameHeight="0"/>
	<SubTexture name="BF NOTE RIGHT00005" x="0" y="0" width="0" height="0" frameX="-107374182" frameY="-107374182" frameWidth="0" frameHeight="0"/>
	<SubTexture name="BF NOTE RIGHT00006" x="0" y="0" width="0" height="0" frameX="-107374182" frameY="-107374182" frameWidth="0" frameHeight="0"/>
	<SubTexture name="BF NOTE RIGHT00007" x="0" y="0" width="0" height="0" frameX="-107374182" frameY="-107374182" frameWidth="0" frameHeight="0"/>
	<SubTexture name="BF NOTE RIGHT00008" x="0" y="0" width="0" height="0" frameX="-107374182" frameY="-107374182" frameWidth="0" frameHeight="0"/>
	<SubTexture name="BF NOTE RIGHT00009" x="0" y="0" width="0" height="0" frameX="-107374182" frameY="-107374182" frameWidth="0" frameHeight="0"/>
	<SubTexture name="BF NOTE RIGHT00010" x="0" y="0" width="0" height="0" frameX="-107374182" frameY="-107374182" frameWidth="0" frameHeight="0"/>
	<SubTexture name="BF NOTE RIGHT00011" x="0" y="0" width="0" height="0" frameX="-107374182" frameY="-107374182" frameWidth="0" frameHeight="0"/>
	<SubTexture name="BF NOTE RIGHT00012" x="0" y="0" width="0" height="0" frameX="-107374182" frameY="-107374182" frameWidth="0" frameHeight="0"/>
	<SubTexture name="BF NOTE RIGHT00013" x="0" y="0" width="0" height="0" frameX="-107374182" frameY="-107374182" frameWidth="0" frameHeight="0"/>
	<SubTexture name="BF NOTE RIGHT00014" x="0" y="0" width="0" height="0" frameX="-107374182" frameY="-107374182" frameWidth="0" frameHeight="0"/>
	<SubTexture name="BF NOTE RIGHT00015" x="0" y="0" width="0" height="0" frameX="-107374182" frameY="-107374182" frameWidth="0" frameHeight="0"/>
	<SubTexture name="BF NOTE RIGHT00016" x="0" y="0" width="0" height="0" frameX="-107374182" frameY="-107374182" frameWidth="0" frameHeight="0"/>
	<SubTexture name="BF NOTE RIGHT00017" x="0" y="0" width="0" height="0" frameX="-107374182" frameY="-107374182" frameWidth="0" frameHeight="0"/>
	<SubTexture name="BF NOTE RIGHT00018" x="0" y="0" width="0" height="0" frameX="-107374182" frameY="-107374182" frameWidth="0" frameHeight="0"/>
	<SubTexture name="BF NOTE UP00000" x="0" y="0" width="0" height="0" frameX="-107374182" frameY="-107374182" frameWidth="0" frameHeight="0"/>
	<SubTexture name="BF NOTE UP00001" x="0" y="0" width="0" height="0" frameX="-107374182" frameY="-107374182" frameWidth="0" frameHeight="0"/>
	<SubTexture name="BF NOTE UP00002" x="0" y="0" width="0" height="0" frameX="-107374182" frameY="-107374182" frameWidth="0" frameHeight="0"/>
	<SubTexture name="BF NOTE UP00003" x="0" y="0" width="0" height="0" frameX="-107374182" frameY="-107374182" frameWidth="0" frameHeight="0"/>
	<SubTexture name="BF NOTE UP00004" x="0" y="0" width="0" height="0" frameX="-107374182" frameY="-107374182" frameWidth="0" frameHeight="0"/>
	<SubTexture name="BF NOTE UP00005" x="0" y="0" width="0" height="0" frameX="-107374182" frameY="-107374182" frameWidth="0" frameHeight="0"/>
	<SubTexture name="BF NOTE UP00006" x="0" y="0" width="0" height="0" frameX="-107374182" frameY="-107374182" frameWidth="0" frameHeight="0"/>
	<SubTexture name="BF NOTE UP00007" x="0" y="0" width="0" height="0" frameX="-107374182" frameY="-107374182" frameWidth="0" frameHeight="0"/>
	<SubTexture name="BF NOTE UP00008" x="0" y="0" width="0" height="0" frameX="-107374182" frameY="-107374182" frameWidth="0" frameHeight="0"/>
	<SubTexture name="BF NOTE UP00009" x="0" y="0" width="0" height="0" frameX="-107374182" frameY="-107374182" frameWidth="0" frameHeight="0"/>
	<SubTexture name="BF NOTE UP00010" x="0" y="0" width="0" height="0" frameX="-107374182" frameY="-107374182" frameWidth="0" frameHeight="0"/>
	<SubTexture name="BF NOTE UP00011" x="0" y="0" width="0" height="0" frameX="-107374182" frameY="-107374182" frameWidth="0" frameHeight="0"/>
	<SubTexture name="BF NOTE UP00012" x="0" y="0" width="0" height="0" frameX="-107374182" frameY="-107374182" frameWidth="0" frameHeight="0"/>
	<SubTexture name="BF NOTE UP00013" x="0" y="0" width="0" height="0" frameX="-107374182" frameY="-107374182" frameWidth="0" frameHeight="0"/>
	<SubTexture name="BF NOTE UP00014" x="0" y="0" width="0" height="0" frameX="-107374182" frameY="-107374182" frameWidth="0" frameHeight="0"/>
	<SubTexture name="BF NOTE UP00015" x="0" y="0" width="0" height="0" frameX="-107374182" frameY="-107374182" frameWidth="0" frameHeight="0"/>
	<SubTexture name="BF NOTE UP00016" x="0" y="0" width="0" height="0" frameX="-107374182" frameY="-107374182" frameWidth="0" frameHeight="0"/>
	<SubTexture name="BF NOTE UP00017" x="0" y="0" width="0" height="0" frameX="-107374182" frameY="-107374182" frameWidth="0" frameHeight="0"/>
	<SubTexture name="BF NOTE UP00018" x="0" y="0" width="0" height="0" frameX="-107374182" frameY="-107374182" frameWidth="0" frameHeight="0"/>
	<SubTexture name="BF NOTE UP00019" x="0" y="0" width="0" height="0" frameX="-107374182" frameY="-107374182" frameWidth="0" frameHeight="0"/>
	<SubTexture name="BF NOTE UP00020" x="0" y="0" width="0" height="0" frameX="-107374182" frameY="-107374182" frameWidth="0" frameHeight="0"/>
	<SubTexture name="BF NOTE UP00021" x="0" y="0" width="0" height="0" frameX="-107374182" frameY="-107374182" frameWidth="0" frameHeight="0"/>
	<SubTexture name="BF NOTE UP00022" x="0" y="0" width="0" height="0" frameX="-107374182" frameY="-107374182" frameWidth="0" frameHeight="0"/>
	<SubTexture name="BF NOTE UP00023" x="0" y="0" width="0" height="0" frameX="-107374182" frameY="-107374182" frameWidth="0" frameHeight="0"/>
	<SubTexture name="BF NOTE UP00024" x="0" y="0" width="0" height="0" frameX="-107374182" frameY="-107374182" frameWidth="0" frameHeight="0"/>
	<SubTexture name="BF NOTE UP00025" x="0" y="0" width="0" height="0" frameX="-107374182" frameY="-107374182" frameWidth="0" frameHeight="0"/>
	<SubTexture name="BF NOTE UP00026" x="0" y="0" width="0" height="0" frameX="-107374182" frameY="-107374182" frameWidth="0" frameHeight="0"/>
	<SubTexture name="BF NOTE UP00027" x="0" y="0" width="0" height="0" frameX="-107374182" frameY="-107374182" frameWidth="0" frameHeight="0"/>
	<SubTexture name="BF NOTE UP00028" x="0" y="0" width="0" height="0" frameX="-107374182" frameY="-107374182" frameWidth="0" frameHeight="0"/>
	<SubTexture name="BF NOTE UP00029" x="0" y="0" width="0" height="0" frameX="-107374182" frameY="-107374182" frameWidth="0" frameHeight="0"/>
	<SubTexture name="BF NOTE UP00030" x="0" y="0" width="0" height="0" frameX="-107374182" frameY="-107374182" frameWidth="0" frameHeight="0"/>
	<SubTexture name="BF NOTE UP00031" x="0" y="0" width="0" height="0" frameX="-107374182" frameY="-107374182" frameWidth="0" frameHeight="0"/>
	<SubTexture name="BF NOTE UP00032" x="0" y="0" width="0" height="0" frameX="-107374182" frameY="-107374182" frameWidth="0" frameHeight="0"/>
	<SubTexture name="BF NOTE UP00033" x="0" y="0" width="0" height="0" frameX="-107374182" frameY="-107374182" frameWidth="0" frameHeight="0"/>
	<SubTexture name="BF NOTE UP00034" x="0" y="0" width="0" height="0" frameX="-107374182" frameY="-107374182" frameWidth="0" frameHeight="0"/>
	<SubTexture name="BF NOTE UP00035" x="0" y="0" width="0" height="0" frameX="-107374182" frameY="-107374182" frameWidth="0" frameHeight="0"/>
	<SubTexture name="BF NOTE UP00036" x="0" y="0" width="0" height="0" frameX="-107374182" frameY="-107374182" frameWidth="0" frameHeight="0"/>
	<SubTexture name="BF NOTE UP00037" x="0" y="0" width="0" height="0" frameX="-107374182" frameY="-107374182" frameWidth="0" frameHeight="0"/>
	<SubTexture name="BF NOTE UP00038" x="0" y="0" width="0" height="0" frameX="-107374182" frameY="-107374182" frameWidth="0" frameHeight="0"/>
	<SubTexture name="BF NOTE UP00039" x="0" y="0" width="0" height="0" frameX="-107374182" frameY="-107374182" frameWidth="0" frameHeight="0"/>
	<SubTexture name="BF NOTE UP00040" x="0" y="0" width="0" height="0" frameX="-107374182" frameY="-107374182" frameWidth="0" frameHeight="0"/>
	<SubTexture name="BF NOTE UP00041" x="0" y="0" width="0" height="0" frameX="-107374182" frameY="-107374182" frameWidth="0" frameHeight="0"/>
	<SubTexture name="BF NOTE UP00042" x="0" y="0" width="0" height="0" frameX="-107374182" frameY="-107374182" frameWidth="0" frameHeight="0"/>
	<SubTexture name="BF NOTE UP00043" x="0" y="0" width="0" height="0" frameX="-107374182" frameY="-107374182" frameWidth="0" frameHeight="0"/>
	<SubTexture name="BF NOTE UP00044" x="0" y="0" width="0" height="0" frameX="-107374182" frameY="-107374182" frameWidth="0" frameHeight="0"/>
	<SubTexture name="BF NOTE UP00045" x="0" y="0" width="0" height="0" frameX="-107374182" frameY="-107374182" frameWidth="0" frameHeight="0"/>
	<SubTexture name="BF NOTE UP00046" x="0" y="0" width="0" height="0" frameX="-107374182" frameY="-107374182" frameWidth="0" frameHeight="0"/>
	<SubTexture name="BF NOTE UP00047" x="0" y="0" width="0" height="0" frameX="-107374182" frameY="-107374182" frameWidth="0" frameHeight="0"/>
	<SubTexture name="BF NOTE UP00048" x="0" y="0" width="0" height="0" frameX="-107374182" frameY="-107374182" frameWidth="0" frameHeight="0"/>
	<SubTexture name="BF NOTE UP00049" x="0" y="0" width="0" height="0" frameX="-107374182" frameY="-107374182" frameWidth="0" frameHeight="0"/>
	<SubTexture name="BF NOTE UP00050" x="0" y="0" width="0" height="0" frameX="-107374182" frameY="-107374182" frameWidth="0" frameHeight="0"/>
	<SubTexture name="BF NOTE UP00051" x="0" y="0" width="0" height="0" frameX="-107374182" frameY="-107374182" frameWidth="0" frameHeight="0"/>
	<SubTexture name="BF NOTE UP00052" x="0" y="0" width="0" height="0" frameX="-107374182" frameY="-107374182" frameWidth="0" frameHeight="0"/>
	<SubTexture name="BF NOTE UP00053" x="0" y="0" width="0" height="0" frameX="-107374182" frameY="-107374182" frameWidth="0" frameHeight="0"/>
	<SubTexture name="BF NOTE UP00054" x="0" y="0" width="0" height="0" frameX="-107374182" frameY="-107374182" frameWidth="0" frameHeight="0"/>
	<SubTexture name="BF NOTE UP00055" x="0" y="0" width="0" height="0" frameX="-107374182" frameY="-107374182" frameWidth="0" frameHeight="0"/>
	<SubTexture name="BF NOTE UP00056" x="0" y="0" width="0" height="0" frameX="-107374182" frameY="-107374182" frameWidth="0" frameHeight="0"/>
	<SubTexture name="BF NOTE UP00057" x="0" y="0" width="0" height="0" frameX="-107374182" frameY="-107374182" frameWidth="0" frameHeight="0"/>
	<SubTexture name="BF NOTE UP00058" x="0" y="0" width="0" height="0" frameX="-107374182" frameY="-107374182" frameWidth="0" frameHeight="0"/>
	<SubTexture name="BF NOTE UP00059" x="0" y="0" width="0" height="0" frameX="-107374182" frameY="-107374182" frameWidth="0" frameHeight="0"/>
	<SubTexture name="BF idle dance0000" x="0" y="0" width="0" height="0" frameX="-107374182" frameY="-107374182" frameWidth="0" frameHeight="0"/>
	<SubTexture name="BF idle dance0001" x="0" y="0" width="0" height="0" frameX="-107374182" frameY="-107374182" frameWidth="0" frameHeight="0"/>
	<SubTexture name="BF idle dance0002" x="0" y="0" width="0" height="0" frameX="-107374182" frameY="-107374182" frameWidth="0" frameHeight="0"/>
	<SubTexture name="BF idle dance0003" x="0" y="0" width="0" height="0" frameX="-107374182" frameY="-107374182" frameWidth="0" frameHeight="0"/>
	<SubTexture name="BF idle dance0004" x="0" y="0" width="0" height="0" frameX="-107374182" frameY="-107374182" frameWidth="0" frameHeight="0"/>
	<SubTexture name="BF idle dance0005" x="0" y="0" width="0" height="0" frameX="-107374182" frameY="-107374182" frameWidth="0" frameHeight="0"/>
	<SubTexture name="BF idle dance0006" x="0" y="0" width="0" height="0" frameX="-107374182" frameY="-107374182" frameWidth="0" frameHeight="0"/>
	<SubTexture name="BF idle dance0007" x="0" y="0" width="0" height="0" frameX="-107374182" frameY="-107374182" frameWidth="0" frameHeight="0"/>
	<SubTexture name="BF idle dance0008" x="0" y="0" width="0" height="0" frameX="-107374182" frameY="-107374182" frameWidth="0" frameHeight="0"/>
	<SubTexture name="BF idle dance0009" x="0" y="0" width="0" height="0" frameX="-107374182" frameY="-107374182" frameWidth="0" frameHeight="0"/>
	<SubTexture name="BF idle dance0010" x="0" y="0" width="0" height="0" frameX="-107374182" frameY="-107374182" frameWidth="0" frameHeight="0"/>
	<SubTexture name="BF idle dance0011" x="0" y="0" width="0" height="0" frameX="-107374182" frameY="-107374182" frameWidth="0" frameHeight="0"/>
	<SubTexture name="BF idle dance0012" x="0" y="0" width="0" height="0" frameX="-107374182" frameY="-107374182" frameWidth="0" frameHeight="0"/>
</TextureAtlas>
